<annotation>
	<folder>images</folder>
	<filename>176.jpg</filename>
	<path>/home/sweekar/Downloads/annotate_nepali/images/176.jpg</path>
	<source>
		<database>Unknown</database>
	</source>
	<size>
		<width>3024</width>
		<height>4032</height>
		<depth>3</depth>
	</size>
	<segmented>0</segmented>
	<object>
		<name>text</name>
		<pose>Unspecified</pose>
		<truncated>0</truncated>
		<difficult>0</difficult>
		<bndbox>
			<xmin>1019</xmin>
			<ymin>80</ymin>
			<xmax>1215</xmax>
			<ymax>155</ymax>
		</bndbox>
	</object>
	<object>
		<name>text</name>
		<pose>Unspecified</pose>
		<truncated>0</truncated>
		<difficult>0</difficult>
		<bndbox>
			<xmin>1215</xmin>
			<ymin>84</ymin>
			<xmax>1300</xmax>
			<ymax>166</ymax>
		</bndbox>
	</object>
	<object>
		<name>text</name>
		<pose>Unspecified</pose>
		<truncated>0</truncated>
		<difficult>0</difficult>
		<bndbox>
			<xmin>244</xmin>
			<ymin>129</ymin>
			<xmax>578</xmax>
			<ymax>218</ymax>
		</bndbox>
	</object>
	<object>
		<name>text</name>
		<pose>Unspecified</pose>
		<truncated>0</truncated>
		<difficult>0</difficult>
		<bndbox>
			<xmin>618</xmin>
			<ymin>161</ymin>
			<xmax>945</xmax>
			<ymax>237</ymax>
		</bndbox>
	</object>
	<object>
		<name>text</name>
		<pose>Unspecified</pose>
		<truncated>0</truncated>
		<difficult>0</difficult>
		<bndbox>
			<xmin>1010</xmin>
			<ymin>167</ymin>
			<xmax>1213</xmax>
			<ymax>256</ymax>
		</bndbox>
	</object>
	<object>
		<name>text</name>
		<pose>Unspecified</pose>
		<truncated>0</truncated>
		<difficult>0</difficult>
		<bndbox>
			<xmin>1250</xmin>
			<ymin>185</ymin>
			<xmax>1872</xmax>
			<ymax>277</ymax>
		</bndbox>
	</object>
	<object>
		<name>text</name>
		<pose>Unspecified</pose>
		<truncated>0</truncated>
		<difficult>0</difficult>
		<bndbox>
			<xmin>1915</xmin>
			<ymin>191</ymin>
			<xmax>2172</xmax>
			<ymax>283</ymax>
		</bndbox>
	</object>
	<object>
		<name>text</name>
		<pose>Unspecified</pose>
		<truncated>0</truncated>
		<difficult>0</difficult>
		<bndbox>
			<xmin>2213</xmin>
			<ymin>169</ymin>
			<xmax>2604</xmax>
			<ymax>269</ymax>
		</bndbox>
	</object>
	<object>
		<name>text</name>
		<pose>Unspecified</pose>
		<truncated>0</truncated>
		<difficult>0</difficult>
		<bndbox>
			<xmin>250</xmin>
			<ymin>213</ymin>
			<xmax>607</xmax>
			<ymax>307</ymax>
		</bndbox>
	</object>
	<object>
		<name>text</name>
		<pose>Unspecified</pose>
		<truncated>0</truncated>
		<difficult>0</difficult>
		<bndbox>
			<xmin>656</xmin>
			<ymin>234</ymin>
			<xmax>1053</xmax>
			<ymax>321</ymax>
		</bndbox>
	</object>
	<object>
		<name>text</name>
		<pose>Unspecified</pose>
		<truncated>0</truncated>
		<difficult>0</difficult>
		<bndbox>
			<xmin>1107</xmin>
			<ymin>272</ymin>
			<xmax>1304</xmax>
			<ymax>334</ymax>
		</bndbox>
	</object>
	<object>
		<name>text</name>
		<pose>Unspecified</pose>
		<truncated>0</truncated>
		<difficult>0</difficult>
		<bndbox>
			<xmin>1364</xmin>
			<ymin>277</ymin>
			<xmax>1604</xmax>
			<ymax>348</ymax>
		</bndbox>
	</object>
	<object>
		<name>text</name>
		<pose>Unspecified</pose>
		<truncated>0</truncated>
		<difficult>0</difficult>
		<bndbox>
			<xmin>1907</xmin>
			<ymin>288</ymin>
			<xmax>2156</xmax>
			<ymax>364</ymax>
		</bndbox>
	</object>
	<object>
		<name>text</name>
		<pose>Unspecified</pose>
		<truncated>0</truncated>
		<difficult>0</difficult>
		<bndbox>
			<xmin>2194</xmin>
			<ymin>275</ymin>
			<xmax>2494</xmax>
			<ymax>345</ymax>
		</bndbox>
	</object>
	<object>
		<name>text</name>
		<pose>Unspecified</pose>
		<truncated>0</truncated>
		<difficult>0</difficult>
		<bndbox>
			<xmin>229</xmin>
			<ymin>299</ymin>
			<xmax>615</xmax>
			<ymax>402</ymax>
		</bndbox>
	</object>
	<object>
		<name>text</name>
		<pose>Unspecified</pose>
		<truncated>0</truncated>
		<difficult>0</difficult>
		<bndbox>
			<xmin>637</xmin>
			<ymin>326</ymin>
			<xmax>826</xmax>
			<ymax>402</ymax>
		</bndbox>
	</object>
	<object>
		<name>text</name>
		<pose>Unspecified</pose>
		<truncated>0</truncated>
		<difficult>0</difficult>
		<bndbox>
			<xmin>896</xmin>
			<ymin>337</ymin>
			<xmax>1185</xmax>
			<ymax>418</ymax>
		</bndbox>
	</object>
	<object>
		<name>text</name>
		<pose>Unspecified</pose>
		<truncated>0</truncated>
		<difficult>0</difficult>
		<bndbox>
			<xmin>1221</xmin>
			<ymin>358</ymin>
			<xmax>1367</xmax>
			<ymax>415</ymax>
		</bndbox>
	</object>
	<object>
		<name>text</name>
		<pose>Unspecified</pose>
		<truncated>0</truncated>
		<difficult>0</difficult>
		<bndbox>
			<xmin>1410</xmin>
			<ymin>353</ymin>
			<xmax>1880</xmax>
			<ymax>437</ymax>
		</bndbox>
	</object>
	<object>
		<name>text</name>
		<pose>Unspecified</pose>
		<truncated>0</truncated>
		<difficult>0</difficult>
		<bndbox>
			<xmin>1940</xmin>
			<ymin>356</ymin>
			<xmax>2077</xmax>
			<ymax>434</ymax>
		</bndbox>
	</object>
	<object>
		<name>text</name>
		<pose>Unspecified</pose>
		<truncated>0</truncated>
		<difficult>0</difficult>
		<bndbox>
			<xmin>2107</xmin>
			<ymin>347</ymin>
			<xmax>2383</xmax>
			<ymax>421</ymax>
		</bndbox>
	</object>
	<object>
		<name>text</name>
		<pose>Unspecified</pose>
		<truncated>0</truncated>
		<difficult>0</difficult>
		<bndbox>
			<xmin>2391</xmin>
			<ymin>337</ymin>
			<xmax>2577</xmax>
			<ymax>396</ymax>
		</bndbox>
	</object>
	<object>
		<name>text</name>
		<pose>Unspecified</pose>
		<truncated>0</truncated>
		<difficult>0</difficult>
		<bndbox>
			<xmin>234</xmin>
			<ymin>396</ymin>
			<xmax>334</xmax>
			<ymax>464</ymax>
		</bndbox>
	</object>
	<object>
		<name>text</name>
		<pose>Unspecified</pose>
		<truncated>0</truncated>
		<difficult>0</difficult>
		<bndbox>
			<xmin>391</xmin>
			<ymin>410</ymin>
			<xmax>615</xmax>
			<ymax>491</ymax>
		</bndbox>
	</object>
	<object>
		<name>text</name>
		<pose>Unspecified</pose>
		<truncated>0</truncated>
		<difficult>0</difficult>
		<bndbox>
			<xmin>656</xmin>
			<ymin>407</ymin>
			<xmax>1053</xmax>
			<ymax>518</ymax>
		</bndbox>
	</object>
	<object>
		<name>text</name>
		<pose>Unspecified</pose>
		<truncated>0</truncated>
		<difficult>0</difficult>
		<bndbox>
			<xmin>242</xmin>
			<ymin>494</ymin>
			<xmax>518</xmax>
			<ymax>594</ymax>
		</bndbox>
	</object>
	<object>
		<name>text</name>
		<pose>Unspecified</pose>
		<truncated>0</truncated>
		<difficult>0</difficult>
		<bndbox>
			<xmin>569</xmin>
			<ymin>513</ymin>
			<xmax>899</xmax>
			<ymax>604</ymax>
		</bndbox>
	</object>
	<object>
		<name>text</name>
		<pose>Unspecified</pose>
		<truncated>0</truncated>
		<difficult>0</difficult>
		<bndbox>
			<xmin>926</xmin>
			<ymin>545</ymin>
			<xmax>1164</xmax>
			<ymax>640</ymax>
		</bndbox>
	</object>
	<object>
		<name>text</name>
		<pose>Unspecified</pose>
		<truncated>0</truncated>
		<difficult>0</difficult>
		<bndbox>
			<xmin>221</xmin>
			<ymin>599</ymin>
			<xmax>604</xmax>
			<ymax>696</ymax>
		</bndbox>
	</object>
	<object>
		<name>text</name>
		<pose>Unspecified</pose>
		<truncated>0</truncated>
		<difficult>0</difficult>
		<bndbox>
			<xmin>634</xmin>
			<ymin>613</ymin>
			<xmax>899</xmax>
			<ymax>704</ymax>
		</bndbox>
	</object>
	<object>
		<name>text</name>
		<pose>Unspecified</pose>
		<truncated>0</truncated>
		<difficult>0</difficult>
		<bndbox>
			<xmin>937</xmin>
			<ymin>642</ymin>
			<xmax>1099</xmax>
			<ymax>710</ymax>
		</bndbox>
	</object>
	<object>
		<name>text</name>
		<pose>Unspecified</pose>
		<truncated>0</truncated>
		<difficult>0</difficult>
		<bndbox>
			<xmin>1110</xmin>
			<ymin>664</ymin>
			<xmax>1180</xmax>
			<ymax>721</ymax>
		</bndbox>
	</object>
	<object>
		<name>text</name>
		<pose>Unspecified</pose>
		<truncated>0</truncated>
		<difficult>0</difficult>
		<bndbox>
			<xmin>231</xmin>
			<ymin>699</ymin>
			<xmax>545</xmax>
			<ymax>783</ymax>
		</bndbox>
	</object>
	<object>
		<name>text</name>
		<pose>Unspecified</pose>
		<truncated>0</truncated>
		<difficult>0</difficult>
		<bndbox>
			<xmin>640</xmin>
			<ymin>829</ymin>
			<xmax>867</xmax>
			<ymax>940</ymax>
		</bndbox>
	</object>
	<object>
		<name>text</name>
		<pose>Unspecified</pose>
		<truncated>0</truncated>
		<difficult>0</difficult>
		<bndbox>
			<xmin>953</xmin>
			<ymin>837</ymin>
			<xmax>1448</xmax>
			<ymax>956</ymax>
		</bndbox>
	</object>
	<object>
		<name>text</name>
		<pose>Unspecified</pose>
		<truncated>0</truncated>
		<difficult>0</difficult>
		<bndbox>
			<xmin>1494</xmin>
			<ymin>867</ymin>
			<xmax>1918</xmax>
			<ymax>969</ymax>
		</bndbox>
	</object>
	<object>
		<name>text</name>
		<pose>Unspecified</pose>
		<truncated>0</truncated>
		<difficult>0</difficult>
		<bndbox>
			<xmin>215</xmin>
			<ymin>883</ymin>
			<xmax>375</xmax>
			<ymax>994</ymax>
		</bndbox>
	</object>
	<object>
		<name>text</name>
		<pose>Unspecified</pose>
		<truncated>0</truncated>
		<difficult>0</difficult>
		<bndbox>
			<xmin>423</xmin>
			<ymin>910</ymin>
			<xmax>580</xmax>
			<ymax>1002</ymax>
		</bndbox>
	</object>
	<object>
		<name>text</name>
		<pose>Unspecified</pose>
		<truncated>0</truncated>
		<difficult>0</difficult>
		<bndbox>
			<xmin>626</xmin>
			<ymin>948</ymin>
			<xmax>1121</xmax>
			<ymax>1040</ymax>
		</bndbox>
	</object>
	<object>
		<name>text</name>
		<pose>Unspecified</pose>
		<truncated>0</truncated>
		<difficult>0</difficult>
		<bndbox>
			<xmin>1167</xmin>
			<ymin>961</ymin>
			<xmax>1380</xmax>
			<ymax>1061</ymax>
		</bndbox>
	</object>
	<object>
		<name>text</name>
		<pose>Unspecified</pose>
		<truncated>0</truncated>
		<difficult>0</difficult>
		<bndbox>
			<xmin>1415</xmin>
			<ymin>985</ymin>
			<xmax>1729</xmax>
			<ymax>1067</ymax>
		</bndbox>
	</object>
	<object>
		<name>text</name>
		<pose>Unspecified</pose>
		<truncated>0</truncated>
		<difficult>0</difficult>
		<bndbox>
			<xmin>1767</xmin>
			<ymin>972</ymin>
			<xmax>2018</xmax>
			<ymax>1061</ymax>
		</bndbox>
	</object>
	<object>
		<name>text</name>
		<pose>Unspecified</pose>
		<truncated>0</truncated>
		<difficult>0</difficult>
		<bndbox>
			<xmin>2067</xmin>
			<ymin>945</ymin>
			<xmax>2510</xmax>
			<ymax>1053</ymax>
		</bndbox>
	</object>
	<object>
		<name>text</name>
		<pose>Unspecified</pose>
		<truncated>0</truncated>
		<difficult>0</difficult>
		<bndbox>
			<xmin>210</xmin>
			<ymin>996</ymin>
			<xmax>677</xmax>
			<ymax>1096</ymax>
		</bndbox>
	</object>
	<object>
		<name>text</name>
		<pose>Unspecified</pose>
		<truncated>0</truncated>
		<difficult>0</difficult>
		<bndbox>
			<xmin>756</xmin>
			<ymin>1034</ymin>
			<xmax>1045</xmax>
			<ymax>1121</ymax>
		</bndbox>
	</object>
	<object>
		<name>text</name>
		<pose>Unspecified</pose>
		<truncated>0</truncated>
		<difficult>0</difficult>
		<bndbox>
			<xmin>1099</xmin>
			<ymin>1045</ymin>
			<xmax>1261</xmax>
			<ymax>1123</ymax>
		</bndbox>
	</object>
	<object>
		<name>text</name>
		<pose>Unspecified</pose>
		<truncated>0</truncated>
		<difficult>0</difficult>
		<bndbox>
			<xmin>1321</xmin>
			<ymin>1072</ymin>
			<xmax>1485</xmax>
			<ymax>1158</ymax>
		</bndbox>
	</object>
	<object>
		<name>text</name>
		<pose>Unspecified</pose>
		<truncated>0</truncated>
		<difficult>0</difficult>
		<bndbox>
			<xmin>1545</xmin>
			<ymin>1069</ymin>
			<xmax>1864</xmax>
			<ymax>1167</ymax>
		</bndbox>
	</object>
	<object>
		<name>text</name>
		<pose>Unspecified</pose>
		<truncated>0</truncated>
		<difficult>0</difficult>
		<bndbox>
			<xmin>1910</xmin>
			<ymin>1061</ymin>
			<xmax>2213</xmax>
			<ymax>1142</ymax>
		</bndbox>
	</object>
	<object>
		<name>text</name>
		<pose>Unspecified</pose>
		<truncated>0</truncated>
		<difficult>0</difficult>
		<bndbox>
			<xmin>2256</xmin>
			<ymin>1040</ymin>
			<xmax>2499</xmax>
			<ymax>1134</ymax>
		</bndbox>
	</object>
	<object>
		<name>text</name>
		<pose>Unspecified</pose>
		<truncated>0</truncated>
		<difficult>0</difficult>
		<bndbox>
			<xmin>204</xmin>
			<ymin>1094</ymin>
			<xmax>713</xmax>
			<ymax>1180</ymax>
		</bndbox>
	</object>
	<object>
		<name>text</name>
		<pose>Unspecified</pose>
		<truncated>0</truncated>
		<difficult>0</difficult>
		<bndbox>
			<xmin>799</xmin>
			<ymin>1123</ymin>
			<xmax>1161</xmax>
			<ymax>1215</ymax>
		</bndbox>
	</object>
	<object>
		<name>text</name>
		<pose>Unspecified</pose>
		<truncated>0</truncated>
		<difficult>0</difficult>
		<bndbox>
			<xmin>1204</xmin>
			<ymin>1129</ymin>
			<xmax>1523</xmax>
			<ymax>1210</ymax>
		</bndbox>
	</object>
	<object>
		<name>text</name>
		<pose>Unspecified</pose>
		<truncated>0</truncated>
		<difficult>0</difficult>
		<bndbox>
			<xmin>1637</xmin>
			<ymin>1140</ymin>
			<xmax>1796</xmax>
			<ymax>1210</ymax>
		</bndbox>
	</object>
	<object>
		<name>text</name>
		<pose>Unspecified</pose>
		<truncated>0</truncated>
		<difficult>0</difficult>
		<bndbox>
			<xmin>1834</xmin>
			<ymin>1145</ymin>
			<xmax>2223</xmax>
			<ymax>1240</ymax>
		</bndbox>
	</object>
	<object>
		<name>text</name>
		<pose>Unspecified</pose>
		<truncated>0</truncated>
		<difficult>0</difficult>
		<bndbox>
			<xmin>2256</xmin>
			<ymin>1134</ymin>
			<xmax>2667</xmax>
			<ymax>1207</ymax>
		</bndbox>
	</object>
	<object>
		<name>text</name>
		<pose>Unspecified</pose>
		<truncated>0</truncated>
		<difficult>0</difficult>
		<bndbox>
			<xmin>153</xmin>
			<ymin>1164</ymin>
			<xmax>353</xmax>
			<ymax>1261</ymax>
		</bndbox>
	</object>
	<object>
		<name>text</name>
		<pose>Unspecified</pose>
		<truncated>0</truncated>
		<difficult>0</difficult>
		<bndbox>
			<xmin>475</xmin>
			<ymin>1207</ymin>
			<xmax>661</xmax>
			<ymax>1283</ymax>
		</bndbox>
	</object>
	<object>
		<name>text</name>
		<pose>Unspecified</pose>
		<truncated>0</truncated>
		<difficult>0</difficult>
		<bndbox>
			<xmin>726</xmin>
			<ymin>1213</ymin>
			<xmax>799</xmax>
			<ymax>1275</ymax>
		</bndbox>
	</object>
	<object>
		<name>text</name>
		<pose>Unspecified</pose>
		<truncated>0</truncated>
		<difficult>0</difficult>
		<bndbox>
			<xmin>880</xmin>
			<ymin>1204</ymin>
			<xmax>1121</xmax>
			<ymax>1294</ymax>
		</bndbox>
	</object>
	<object>
		<name>text</name>
		<pose>Unspecified</pose>
		<truncated>0</truncated>
		<difficult>0</difficult>
		<bndbox>
			<xmin>1180</xmin>
			<ymin>1207</ymin>
			<xmax>1567</xmax>
			<ymax>1321</ymax>
		</bndbox>
	</object>
	<object>
		<name>text</name>
		<pose>Unspecified</pose>
		<truncated>0</truncated>
		<difficult>0</difficult>
		<bndbox>
			<xmin>1618</xmin>
			<ymin>1210</ymin>
			<xmax>1923</xmax>
			<ymax>1321</ymax>
		</bndbox>
	</object>
	<object>
		<name>text</name>
		<pose>Unspecified</pose>
		<truncated>0</truncated>
		<difficult>0</difficult>
		<bndbox>
			<xmin>2150</xmin>
			<ymin>1229</ymin>
			<xmax>2364</xmax>
			<ymax>1304</ymax>
		</bndbox>
	</object>
	<object>
		<name>text</name>
		<pose>Unspecified</pose>
		<truncated>0</truncated>
		<difficult>0</difficult>
		<bndbox>
			<xmin>2410</xmin>
			<ymin>1215</ymin>
			<xmax>2658</xmax>
			<ymax>1296</ymax>
		</bndbox>
	</object>
	<object>
		<name>text</name>
		<pose>Unspecified</pose>
		<truncated>0</truncated>
		<difficult>0</difficult>
		<bndbox>
			<xmin>140</xmin>
			<ymin>1277</ymin>
			<xmax>356</xmax>
			<ymax>1372</ymax>
		</bndbox>
	</object>
	<object>
		<name>text</name>
		<pose>Unspecified</pose>
		<truncated>0</truncated>
		<difficult>0</difficult>
		<bndbox>
			<xmin>431</xmin>
			<ymin>1283</ymin>
			<xmax>829</xmax>
			<ymax>1380</ymax>
		</bndbox>
	</object>
	<object>
		<name>text</name>
		<pose>Unspecified</pose>
		<truncated>0</truncated>
		<difficult>0</difficult>
		<bndbox>
			<xmin>934</xmin>
			<ymin>1310</ymin>
			<xmax>1153</xmax>
			<ymax>1391</ymax>
		</bndbox>
	</object>
	<object>
		<name>text</name>
		<pose>Unspecified</pose>
		<truncated>0</truncated>
		<difficult>0</difficult>
		<bndbox>
			<xmin>1218</xmin>
			<ymin>1323</ymin>
			<xmax>1461</xmax>
			<ymax>1402</ymax>
		</bndbox>
	</object>
	<object>
		<name>text</name>
		<pose>Unspecified</pose>
		<truncated>0</truncated>
		<difficult>0</difficult>
		<bndbox>
			<xmin>1548</xmin>
			<ymin>1323</ymin>
			<xmax>1780</xmax>
			<ymax>1402</ymax>
		</bndbox>
	</object>
	<object>
		<name>text</name>
		<pose>Unspecified</pose>
		<truncated>0</truncated>
		<difficult>0</difficult>
		<bndbox>
			<xmin>1831</xmin>
			<ymin>1321</ymin>
			<xmax>2067</xmax>
			<ymax>1394</ymax>
		</bndbox>
	</object>
	<object>
		<name>text</name>
		<pose>Unspecified</pose>
		<truncated>0</truncated>
		<difficult>0</difficult>
		<bndbox>
			<xmin>2110</xmin>
			<ymin>1310</ymin>
			<xmax>2234</xmax>
			<ymax>1385</ymax>
		</bndbox>
	</object>
	<object>
		<name>text</name>
		<pose>Unspecified</pose>
		<truncated>0</truncated>
		<difficult>0</difficult>
		<bndbox>
			<xmin>2280</xmin>
			<ymin>1294</ymin>
			<xmax>2453</xmax>
			<ymax>1375</ymax>
		</bndbox>
	</object>
	<object>
		<name>text</name>
		<pose>Unspecified</pose>
		<truncated>0</truncated>
		<difficult>0</difficult>
		<bndbox>
			<xmin>158</xmin>
			<ymin>1383</ymin>
			<xmax>661</xmax>
			<ymax>1469</ymax>
		</bndbox>
	</object>
	<object>
		<name>text</name>
		<pose>Unspecified</pose>
		<truncated>0</truncated>
		<difficult>0</difficult>
		<bndbox>
			<xmin>745</xmin>
			<ymin>1380</ymin>
			<xmax>1080</xmax>
			<ymax>1483</ymax>
		</bndbox>
	</object>
	<object>
		<name>text</name>
		<pose>Unspecified</pose>
		<truncated>0</truncated>
		<difficult>0</difficult>
		<bndbox>
			<xmin>1134</xmin>
			<ymin>1388</ymin>
			<xmax>1588</xmax>
			<ymax>1477</ymax>
		</bndbox>
	</object>
	<object>
		<name>text</name>
		<pose>Unspecified</pose>
		<truncated>0</truncated>
		<difficult>0</difficult>
		<bndbox>
			<xmin>1653</xmin>
			<ymin>1402</ymin>
			<xmax>1821</xmax>
			<ymax>1485</ymax>
		</bndbox>
	</object>
	<object>
		<name>text</name>
		<pose>Unspecified</pose>
		<truncated>0</truncated>
		<difficult>0</difficult>
		<bndbox>
			<xmin>1880</xmin>
			<ymin>1404</ymin>
			<xmax>2115</xmax>
			<ymax>1477</ymax>
		</bndbox>
	</object>
	<object>
		<name>text</name>
		<pose>Unspecified</pose>
		<truncated>0</truncated>
		<difficult>0</difficult>
		<bndbox>
			<xmin>2169</xmin>
			<ymin>1394</ymin>
			<xmax>2599</xmax>
			<ymax>1480</ymax>
		</bndbox>
	</object>
	<object>
		<name>text</name>
		<pose>Unspecified</pose>
		<truncated>0</truncated>
		<difficult>0</difficult>
		<bndbox>
			<xmin>142</xmin>
			<ymin>1477</ymin>
			<xmax>472</xmax>
			<ymax>1569</ymax>
		</bndbox>
	</object>
	<object>
		<name>text</name>
		<pose>Unspecified</pose>
		<truncated>0</truncated>
		<difficult>0</difficult>
		<bndbox>
			<xmin>518</xmin>
			<ymin>1477</ymin>
			<xmax>764</xmax>
			<ymax>1580</ymax>
		</bndbox>
	</object>
	<object>
		<name>text</name>
		<pose>Unspecified</pose>
		<truncated>0</truncated>
		<difficult>0</difficult>
		<bndbox>
			<xmin>842</xmin>
			<ymin>1510</ymin>
			<xmax>915</xmax>
			<ymax>1572</ymax>
		</bndbox>
	</object>
	<object>
		<name>text</name>
		<pose>Unspecified</pose>
		<truncated>0</truncated>
		<difficult>0</difficult>
		<bndbox>
			<xmin>975</xmin>
			<ymin>1494</ymin>
			<xmax>1431</xmax>
			<ymax>1599</ymax>
		</bndbox>
	</object>
	<object>
		<name>text</name>
		<pose>Unspecified</pose>
		<truncated>0</truncated>
		<difficult>0</difficult>
		<bndbox>
			<xmin>1502</xmin>
			<ymin>1494</ymin>
			<xmax>2037</xmax>
			<ymax>1585</ymax>
		</bndbox>
	</object>
	<object>
		<name>text</name>
		<pose>Unspecified</pose>
		<truncated>0</truncated>
		<difficult>0</difficult>
		<bndbox>
			<xmin>2099</xmin>
			<ymin>1483</ymin>
			<xmax>2377</xmax>
			<ymax>1577</ymax>
		</bndbox>
	</object>
	<object>
		<name>text</name>
		<pose>Unspecified</pose>
		<truncated>0</truncated>
		<difficult>0</difficult>
		<bndbox>
			<xmin>2413</xmin>
			<ymin>1480</ymin>
			<xmax>2510</xmax>
			<ymax>1591</ymax>
		</bndbox>
	</object>
	<object>
		<name>text</name>
		<pose>Unspecified</pose>
		<truncated>0</truncated>
		<difficult>0</difficult>
		<bndbox>
			<xmin>118</xmin>
			<ymin>1569</ymin>
			<xmax>461</xmax>
			<ymax>1664</ymax>
		</bndbox>
	</object>
	<object>
		<name>text</name>
		<pose>Unspecified</pose>
		<truncated>0</truncated>
		<difficult>0</difficult>
		<bndbox>
			<xmin>523</xmin>
			<ymin>1580</ymin>
			<xmax>750</xmax>
			<ymax>1677</ymax>
		</bndbox>
	</object>
	<object>
		<name>text</name>
		<pose>Unspecified</pose>
		<truncated>0</truncated>
		<difficult>0</difficult>
		<bndbox>
			<xmin>799</xmin>
			<ymin>1583</ymin>
			<xmax>875</xmax>
			<ymax>1685</ymax>
		</bndbox>
	</object>
	<object>
		<name>text</name>
		<pose>Unspecified</pose>
		<truncated>0</truncated>
		<difficult>0</difficult>
		<bndbox>
			<xmin>994</xmin>
			<ymin>1607</ymin>
			<xmax>1169</xmax>
			<ymax>1713</ymax>
		</bndbox>
	</object>
	<object>
		<name>text</name>
		<pose>Unspecified</pose>
		<truncated>0</truncated>
		<difficult>0</difficult>
		<bndbox>
			<xmin>1264</xmin>
			<ymin>1604</ymin>
			<xmax>1450</xmax>
			<ymax>1704</ymax>
		</bndbox>
	</object>
	<object>
		<name>text</name>
		<pose>Unspecified</pose>
		<truncated>0</truncated>
		<difficult>0</difficult>
		<bndbox>
			<xmin>1515</xmin>
			<ymin>1596</ymin>
			<xmax>2118</xmax>
			<ymax>1718</ymax>
		</bndbox>
	</object>
	<object>
		<name>text</name>
		<pose>Unspecified</pose>
		<truncated>0</truncated>
		<difficult>0</difficult>
		<bndbox>
			<xmin>2175</xmin>
			<ymin>1594</ymin>
			<xmax>2467</xmax>
			<ymax>1718</ymax>
		</bndbox>
	</object>
	<object>
		<name>text</name>
		<pose>Unspecified</pose>
		<truncated>0</truncated>
		<difficult>0</difficult>
		<bndbox>
			<xmin>2502</xmin>
			<ymin>1613</ymin>
			<xmax>2583</xmax>
			<ymax>1723</ymax>
		</bndbox>
	</object>
	<object>
		<name>text</name>
		<pose>Unspecified</pose>
		<truncated>0</truncated>
		<difficult>0</difficult>
		<bndbox>
			<xmin>91</xmin>
			<ymin>1672</ymin>
			<xmax>402</xmax>
			<ymax>1777</ymax>
		</bndbox>
	</object>
	<object>
		<name>text</name>
		<pose>Unspecified</pose>
		<truncated>0</truncated>
		<difficult>0</difficult>
		<bndbox>
			<xmin>542</xmin>
			<ymin>1677</ymin>
			<xmax>704</xmax>
			<ymax>1794</ymax>
		</bndbox>
	</object>
	<object>
		<name>text</name>
		<pose>Unspecified</pose>
		<truncated>0</truncated>
		<difficult>0</difficult>
		<bndbox>
			<xmin>756</xmin>
			<ymin>1683</ymin>
			<xmax>956</xmax>
			<ymax>1804</ymax>
		</bndbox>
	</object>
	<object>
		<name>text</name>
		<pose>Unspecified</pose>
		<truncated>0</truncated>
		<difficult>0</difficult>
		<bndbox>
			<xmin>1026</xmin>
			<ymin>1713</ymin>
			<xmax>1502</xmax>
			<ymax>1823</ymax>
		</bndbox>
	</object>
	<object>
		<name>text</name>
		<pose>Unspecified</pose>
		<truncated>0</truncated>
		<difficult>0</difficult>
		<bndbox>
			<xmin>1553</xmin>
			<ymin>1721</ymin>
			<xmax>1721</xmax>
			<ymax>1796</ymax>
		</bndbox>
	</object>
	<object>
		<name>text</name>
		<pose>Unspecified</pose>
		<truncated>0</truncated>
		<difficult>0</difficult>
		<bndbox>
			<xmin>1764</xmin>
			<ymin>1723</ymin>
			<xmax>2194</xmax>
			<ymax>1821</ymax>
		</bndbox>
	</object>
	<object>
		<name>text</name>
		<pose>Unspecified</pose>
		<truncated>0</truncated>
		<difficult>0</difficult>
		<bndbox>
			<xmin>2061</xmin>
			<ymin>1853</ymin>
			<xmax>2410</xmax>
			<ymax>1972</ymax>
		</bndbox>
	</object>
	<object>
		<name>text</name>
		<pose>Unspecified</pose>
		<truncated>0</truncated>
		<difficult>0</difficult>
		<bndbox>
			<xmin>1972</xmin>
			<ymin>1975</ymin>
			<xmax>2123</xmax>
			<ymax>2064</ymax>
		</bndbox>
	</object>
	<object>
		<name>text</name>
		<pose>Unspecified</pose>
		<truncated>0</truncated>
		<difficult>0</difficult>
		<bndbox>
			<xmin>2069</xmin>
			<ymin>2077</ymin>
			<xmax>2223</xmax>
			<ymax>2167</ymax>
		</bndbox>
	</object>
	<object>
		<name>text</name>
		<pose>Unspecified</pose>
		<truncated>0</truncated>
		<difficult>0</difficult>
		<bndbox>
			<xmin>2261</xmin>
			<ymin>2080</ymin>
			<xmax>2450</xmax>
			<ymax>2164</ymax>
		</bndbox>
	</object>
	<object>
		<name>text</name>
		<pose>Unspecified</pose>
		<truncated>0</truncated>
		<difficult>0</difficult>
		<bndbox>
			<xmin>2499</xmin>
			<ymin>2042</ymin>
			<xmax>2656</xmax>
			<ymax>2156</ymax>
		</bndbox>
	</object>
	<object>
		<name>text</name>
		<pose>Unspecified</pose>
		<truncated>0</truncated>
		<difficult>0</difficult>
		<bndbox>
			<xmin>104</xmin>
			<ymin>2223</ymin>
			<xmax>477</xmax>
			<ymax>2342</ymax>
		</bndbox>
	</object>
	<object>
		<name>text</name>
		<pose>Unspecified</pose>
		<truncated>0</truncated>
		<difficult>0</difficult>
		<bndbox>
			<xmin>556</xmin>
			<ymin>2231</ymin>
			<xmax>821</xmax>
			<ymax>2337</ymax>
		</bndbox>
	</object>
	<object>
		<name>text</name>
		<pose>Unspecified</pose>
		<truncated>0</truncated>
		<difficult>0</difficult>
		<bndbox>
			<xmin>899</xmin>
			<ymin>2237</ymin>
			<xmax>1269</xmax>
			<ymax>2356</ymax>
		</bndbox>
	</object>
	<object>
		<name>text</name>
		<pose>Unspecified</pose>
		<truncated>0</truncated>
		<difficult>0</difficult>
		<bndbox>
			<xmin>1234</xmin>
			<ymin>2229</ymin>
			<xmax>1404</xmax>
			<ymax>2288</ymax>
		</bndbox>
	</object>
	<object>
		<name>text</name>
		<pose>Unspecified</pose>
		<truncated>0</truncated>
		<difficult>0</difficult>
		<bndbox>
			<xmin>1431</xmin>
			<ymin>2234</ymin>
			<xmax>1502</xmax>
			<ymax>2313</ymax>
		</bndbox>
	</object>
	<object>
		<name>text</name>
		<pose>Unspecified</pose>
		<truncated>0</truncated>
		<difficult>0</difficult>
		<bndbox>
			<xmin>1440</xmin>
			<ymin>2285</ymin>
			<xmax>1869</xmax>
			<ymax>2358</ymax>
		</bndbox>
	</object>
	<object>
		<name>text</name>
		<pose>Unspecified</pose>
		<truncated>0</truncated>
		<difficult>0</difficult>
		<bndbox>
			<xmin>1921</xmin>
			<ymin>2269</ymin>
			<xmax>2085</xmax>
			<ymax>2358</ymax>
		</bndbox>
	</object>
	<object>
		<name>text</name>
		<pose>Unspecified</pose>
		<truncated>0</truncated>
		<difficult>0</difficult>
		<bndbox>
			<xmin>2164</xmin>
			<ymin>2248</ymin>
			<xmax>2567</xmax>
			<ymax>2358</ymax>
		</bndbox>
	</object>
	<object>
		<name>text</name>
		<pose>Unspecified</pose>
		<truncated>0</truncated>
		<difficult>0</difficult>
		<bndbox>
			<xmin>94</xmin>
			<ymin>2342</ymin>
			<xmax>607</xmax>
			<ymax>2429</ymax>
		</bndbox>
	</object>
	<object>
		<name>text</name>
		<pose>Unspecified</pose>
		<truncated>0</truncated>
		<difficult>0</difficult>
		<bndbox>
			<xmin>658</xmin>
			<ymin>2353</ymin>
			<xmax>953</xmax>
			<ymax>2442</ymax>
		</bndbox>
	</object>
	<object>
		<name>text</name>
		<pose>Unspecified</pose>
		<truncated>0</truncated>
		<difficult>0</difficult>
		<bndbox>
			<xmin>1018</xmin>
			<ymin>2342</ymin>
			<xmax>1280</xmax>
			<ymax>2426</ymax>
		</bndbox>
	</object>
	<object>
		<name>text</name>
		<pose>Unspecified</pose>
		<truncated>0</truncated>
		<difficult>0</difficult>
		<bndbox>
			<xmin>1334</xmin>
			<ymin>2345</ymin>
			<xmax>1785</xmax>
			<ymax>2437</ymax>
		</bndbox>
	</object>
	<object>
		<name>text</name>
		<pose>Unspecified</pose>
		<truncated>0</truncated>
		<difficult>0</difficult>
		<bndbox>
			<xmin>867</xmin>
			<ymin>2888</ymin>
			<xmax>1123</xmax>
			<ymax>3042</ymax>
		</bndbox>
	</object>
	<object>
		<name>text</name>
		<pose>Unspecified</pose>
		<truncated>0</truncated>
		<difficult>0</difficult>
		<bndbox>
			<xmin>1245</xmin>
			<ymin>2888</ymin>
			<xmax>1518</xmax>
			<ymax>3040</ymax>
		</bndbox>
	</object>
	<object>
		<name>text</name>
		<pose>Unspecified</pose>
		<truncated>0</truncated>
		<difficult>0</difficult>
		<bndbox>
			<xmin>1664</xmin>
			<ymin>2869</ymin>
			<xmax>1904</xmax>
			<ymax>3021</ymax>
		</bndbox>
	</object>
	<object>
		<name>text</name>
		<pose>Unspecified</pose>
		<truncated>0</truncated>
		<difficult>0</difficult>
		<bndbox>
			<xmin>856</xmin>
			<ymin>3080</ymin>
			<xmax>1250</xmax>
			<ymax>3164</ymax>
		</bndbox>
	</object>
	<object>
		<name>text</name>
		<pose>Unspecified</pose>
		<truncated>0</truncated>
		<difficult>0</difficult>
		<bndbox>
			<xmin>1337</xmin>
			<ymin>3045</ymin>
			<xmax>1740</xmax>
			<ymax>3161</ymax>
		</bndbox>
	</object>
	<object>
		<name>text</name>
		<pose>Unspecified</pose>
		<truncated>0</truncated>
		<difficult>0</difficult>
		<bndbox>
			<xmin>1785</xmin>
			<ymin>3075</ymin>
			<xmax>1848</xmax>
			<ymax>3145</ymax>
		</bndbox>
	</object>
	<object>
		<name>text</name>
		<pose>Unspecified</pose>
		<truncated>0</truncated>
		<difficult>0</difficult>
		<bndbox>
			<xmin>1888</xmin>
			<ymin>3021</ymin>
			<xmax>2150</xmax>
			<ymax>3150</ymax>
		</bndbox>
	</object>
	<object>
		<name>text</name>
		<pose>Unspecified</pose>
		<truncated>0</truncated>
		<difficult>0</difficult>
		<bndbox>
			<xmin>853</xmin>
			<ymin>3188</ymin>
			<xmax>1264</xmax>
			<ymax>3299</ymax>
		</bndbox>
	</object>
	<object>
		<name>text</name>
		<pose>Unspecified</pose>
		<truncated>0</truncated>
		<difficult>0</difficult>
		<bndbox>
			<xmin>1304</xmin>
			<ymin>3172</ymin>
			<xmax>1650</xmax>
			<ymax>3299</ymax>
		</bndbox>
	</object>
	<object>
		<name>text</name>
		<pose>Unspecified</pose>
		<truncated>0</truncated>
		<difficult>0</difficult>
		<bndbox>
			<xmin>1683</xmin>
			<ymin>3158</ymin>
			<xmax>1931</xmax>
			<ymax>3277</ymax>
		</bndbox>
	</object>
	<object>
		<name>text</name>
		<pose>Unspecified</pose>
		<truncated>0</truncated>
		<difficult>0</difficult>
		<bndbox>
			<xmin>856</xmin>
			<ymin>3320</ymin>
			<xmax>1045</xmax>
			<ymax>3415</ymax>
		</bndbox>
	</object>
	<object>
		<name>text</name>
		<pose>Unspecified</pose>
		<truncated>0</truncated>
		<difficult>0</difficult>
		<bndbox>
			<xmin>1104</xmin>
			<ymin>3304</ymin>
			<xmax>1518</xmax>
			<ymax>3423</ymax>
		</bndbox>
	</object>
	<object>
		<name>text</name>
		<pose>Unspecified</pose>
		<truncated>0</truncated>
		<difficult>0</difficult>
		<bndbox>
			<xmin>1585</xmin>
			<ymin>3291</ymin>
			<xmax>1726</xmax>
			<ymax>3418</ymax>
		</bndbox>
	</object>
	<object>
		<name>text</name>
		<pose>Unspecified</pose>
		<truncated>0</truncated>
		<difficult>0</difficult>
		<bndbox>
			<xmin>1767</xmin>
			<ymin>3291</ymin>
			<xmax>2010</xmax>
			<ymax>3407</ymax>
		</bndbox>
	</object>
	<object>
		<name>text</name>
		<pose>Unspecified</pose>
		<truncated>0</truncated>
		<difficult>0</difficult>
		<bndbox>
			<xmin>850</xmin>
			<ymin>3445</ymin>
			<xmax>1091</xmax>
			<ymax>3558</ymax>
		</bndbox>
	</object>
	<object>
		<name>text</name>
		<pose>Unspecified</pose>
		<truncated>0</truncated>
		<difficult>0</difficult>
		<bndbox>
			<xmin>1121</xmin>
			<ymin>3458</ymin>
			<xmax>1196</xmax>
			<ymax>3545</ymax>
		</bndbox>
	</object>
	<object>
		<name>text</name>
		<pose>Unspecified</pose>
		<truncated>0</truncated>
		<difficult>0</difficult>
		<bndbox>
			<xmin>1226</xmin>
			<ymin>3421</ymin>
			<xmax>1583</xmax>
			<ymax>3540</ymax>
		</bndbox>
	</object>
	<object>
		<name>text</name>
		<pose>Unspecified</pose>
		<truncated>0</truncated>
		<difficult>0</difficult>
		<bndbox>
			<xmin>1623</xmin>
			<ymin>3421</ymin>
			<xmax>1880</xmax>
			<ymax>3545</ymax>
		</bndbox>
	</object>
	<object>
		<name>text</name>
		<pose>Unspecified</pose>
		<truncated>0</truncated>
		<difficult>0</difficult>
		<bndbox>
			<xmin>1307</xmin>
			<ymin>3531</ymin>
			<xmax>1456</xmax>
			<ymax>3658</ymax>
		</bndbox>
	</object>
	<object>
		<name>text</name>
		<pose>Unspecified</pose>
		<truncated>0</truncated>
		<difficult>0</difficult>
		<bndbox>
			<xmin>1975</xmin>
			<ymin>3502</ymin>
			<xmax>2275</xmax>
			<ymax>3621</ymax>
		</bndbox>
	</object>
	<object>
		<name>text</name>
		<pose>Unspecified</pose>
		<truncated>0</truncated>
		<difficult>0</difficult>
		<bndbox>
			<xmin>2304</xmin>
			<ymin>3491</ymin>
			<xmax>2591</xmax>
			<ymax>3618</ymax>
		</bndbox>
	</object>
	<object>
		<name>text</name>
		<pose>Unspecified</pose>
		<truncated>0</truncated>
		<difficult>0</difficult>
		<bndbox>
			<xmin>2004</xmin>
			<ymin>3629</ymin>
			<xmax>2207</xmax>
			<ymax>3734</ymax>
		</bndbox>
	</object>
	<object>
		<name>text</name>
		<pose>Unspecified</pose>
		<truncated>0</truncated>
		<difficult>0</difficult>
		<bndbox>
			<xmin>2299</xmin>
			<ymin>3621</ymin>
			<xmax>2634</xmax>
			<ymax>3723</ymax>
		</bndbox>
	</object>
	<object>
		<name>text</name>
		<pose>Unspecified</pose>
		<truncated>0</truncated>
		<difficult>0</difficult>
		<bndbox>
			<xmin>272</xmin>
			<ymin>3215</ymin>
			<xmax>418</xmax>
			<ymax>3637</ymax>
		</bndbox>
	</object>
	<object>
		<name>text</name>
		<pose>Unspecified</pose>
		<truncated>0</truncated>
		<difficult>0</difficult>
		<bndbox>
			<xmin>331</xmin>
			<ymin>2850</ymin>
			<xmax>442</xmax>
			<ymax>3126</ymax>
		</bndbox>
	</object>
	<object>
		<name>text</name>
		<pose>Unspecified</pose>
		<truncated>0</truncated>
		<difficult>0</difficult>
		<bndbox>
			<xmin>448</xmin>
			<ymin>2756</ymin>
			<xmax>564</xmax>
			<ymax>3318</ymax>
		</bndbox>
	</object>
	<object>
		<name>text</name>
		<pose>Unspecified</pose>
		<truncated>0</truncated>
		<difficult>0</difficult>
		<bndbox>
			<xmin>421</xmin>
			<ymin>3391</ymin>
			<xmax>537</xmax>
			<ymax>3623</ymax>
		</bndbox>
	</object>
	<object>
		<name>text</name>
		<pose>Unspecified</pose>
		<truncated>0</truncated>
		<difficult>0</difficult>
		<bndbox>
			<xmin>577</xmin>
			<ymin>2983</ymin>
			<xmax>691</xmax>
			<ymax>3339</ymax>
		</bndbox>
	</object>
	<object>
		<name>text</name>
		<pose>Unspecified</pose>
		<truncated>0</truncated>
		<difficult>0</difficult>
		<bndbox>
			<xmin>2185</xmin>
			<ymin>2753</ymin>
			<xmax>2304</xmax>
			<ymax>2967</ymax>
		</bndbox>
	</object>
	<object>
		<name>text</name>
		<pose>Unspecified</pose>
		<truncated>0</truncated>
		<difficult>0</difficult>
		<bndbox>
			<xmin>2302</xmin>
			<ymin>2669</ymin>
			<xmax>2421</xmax>
			<ymax>2858</ymax>
		</bndbox>
	</object>
	<object>
		<name>text</name>
		<pose>Unspecified</pose>
		<truncated>0</truncated>
		<difficult>0</difficult>
		<bndbox>
			<xmin>2199</xmin>
			<ymin>3037</ymin>
			<xmax>2321</xmax>
			<ymax>3264</ymax>
		</bndbox>
	</object>
	<object>
		<name>text</name>
		<pose>Unspecified</pose>
		<truncated>0</truncated>
		<difficult>0</difficult>
		<bndbox>
			<xmin>2337</xmin>
			<ymin>2899</ymin>
			<xmax>2437</xmax>
			<ymax>3218</ymax>
		</bndbox>
	</object>
</annotation>
