<annotation>
	<folder>Youth(906-927)</folder>
	<filename>920.jpg</filename>
	<path>/home/sweekar/Downloads/annotate_nepali/Youth(906-927)/920.jpg</path>
	<source>
		<database>Unknown</database>
	</source>
	<size>
		<width>1079</width>
		<height>640</height>
		<depth>3</depth>
	</size>
	<segmented>0</segmented>
	<object>
		<name>text</name>
		<pose>Unspecified</pose>
		<truncated>0</truncated>
		<difficult>0</difficult>
		<bndbox>
			<xmin>182</xmin>
			<ymin>38</ymin>
			<xmax>311</xmax>
			<ymax>69</ymax>
		</bndbox>
	</object>
	<object>
		<name>text</name>
		<pose>Unspecified</pose>
		<truncated>0</truncated>
		<difficult>0</difficult>
		<bndbox>
			<xmin>323</xmin>
			<ymin>30</ymin>
			<xmax>381</xmax>
			<ymax>68</ymax>
		</bndbox>
	</object>
	<object>
		<name>text</name>
		<pose>Unspecified</pose>
		<truncated>0</truncated>
		<difficult>0</difficult>
		<bndbox>
			<xmin>387</xmin>
			<ymin>40</ymin>
			<xmax>475</xmax>
			<ymax>83</ymax>
		</bndbox>
	</object>
	<object>
		<name>text</name>
		<pose>Unspecified</pose>
		<truncated>0</truncated>
		<difficult>0</difficult>
		<bndbox>
			<xmin>479</xmin>
			<ymin>36</ymin>
			<xmax>528</xmax>
			<ymax>71</ymax>
		</bndbox>
	</object>
	<object>
		<name>text</name>
		<pose>Unspecified</pose>
		<truncated>0</truncated>
		<difficult>0</difficult>
		<bndbox>
			<xmin>533</xmin>
			<ymin>38</ymin>
			<xmax>647</xmax>
			<ymax>78</ymax>
		</bndbox>
	</object>
	<object>
		<name>text</name>
		<pose>Unspecified</pose>
		<truncated>0</truncated>
		<difficult>0</difficult>
		<bndbox>
			<xmin>711</xmin>
			<ymin>42</ymin>
			<xmax>747</xmax>
			<ymax>78</ymax>
		</bndbox>
	</object>
	<object>
		<name>text</name>
		<pose>Unspecified</pose>
		<truncated>0</truncated>
		<difficult>0</difficult>
		<bndbox>
			<xmin>145</xmin>
			<ymin>46</ymin>
			<xmax>164</xmax>
			<ymax>78</ymax>
		</bndbox>
	</object>
	<object>
		<name>text</name>
		<pose>Unspecified</pose>
		<truncated>0</truncated>
		<difficult>0</difficult>
		<bndbox>
			<xmin>143</xmin>
			<ymin>126</ymin>
			<xmax>168</xmax>
			<ymax>152</ymax>
		</bndbox>
	</object>
	<object>
		<name>text</name>
		<pose>Unspecified</pose>
		<truncated>0</truncated>
		<difficult>0</difficult>
		<bndbox>
			<xmin>149</xmin>
			<ymin>212</ymin>
			<xmax>173</xmax>
			<ymax>236</ymax>
		</bndbox>
	</object>
	<object>
		<name>text</name>
		<pose>Unspecified</pose>
		<truncated>0</truncated>
		<difficult>0</difficult>
		<bndbox>
			<xmin>157</xmin>
			<ymin>268</ymin>
			<xmax>180</xmax>
			<ymax>289</ymax>
		</bndbox>
	</object>
	<object>
		<name>text</name>
		<pose>Unspecified</pose>
		<truncated>0</truncated>
		<difficult>0</difficult>
		<bndbox>
			<xmin>144</xmin>
			<ymin>365</ymin>
			<xmax>167</xmax>
			<ymax>389</ymax>
		</bndbox>
	</object>
	<object>
		<name>text</name>
		<pose>Unspecified</pose>
		<truncated>0</truncated>
		<difficult>0</difficult>
		<bndbox>
			<xmin>145</xmin>
			<ymin>462</ymin>
			<xmax>166</xmax>
			<ymax>491</ymax>
		</bndbox>
	</object>
	<object>
		<name>text</name>
		<pose>Unspecified</pose>
		<truncated>0</truncated>
		<difficult>0</difficult>
		<bndbox>
			<xmin>754</xmin>
			<ymin>55</ymin>
			<xmax>875</xmax>
			<ymax>90</ymax>
		</bndbox>
	</object>
	<object>
		<name>text</name>
		<pose>Unspecified</pose>
		<truncated>0</truncated>
		<difficult>0</difficult>
		<bndbox>
			<xmin>885</xmin>
			<ymin>62</ymin>
			<xmax>970</xmax>
			<ymax>102</ymax>
		</bndbox>
	</object>
	<object>
		<name>text</name>
		<pose>Unspecified</pose>
		<truncated>0</truncated>
		<difficult>0</difficult>
		<bndbox>
			<xmin>480</xmin>
			<ymin>78</ymin>
			<xmax>509</xmax>
			<ymax>114</ymax>
		</bndbox>
	</object>
	<object>
		<name>text</name>
		<pose>Unspecified</pose>
		<truncated>0</truncated>
		<difficult>0</difficult>
		<bndbox>
			<xmin>576</xmin>
			<ymin>86</ymin>
			<xmax>623</xmax>
			<ymax>128</ymax>
		</bndbox>
	</object>
	<object>
		<name>text</name>
		<pose>Unspecified</pose>
		<truncated>0</truncated>
		<difficult>0</difficult>
		<bndbox>
			<xmin>634</xmin>
			<ymin>78</ymin>
			<xmax>681</xmax>
			<ymax>117</ymax>
		</bndbox>
	</object>
	<object>
		<name>text</name>
		<pose>Unspecified</pose>
		<truncated>0</truncated>
		<difficult>0</difficult>
		<bndbox>
			<xmin>191</xmin>
			<ymin>74</ymin>
			<xmax>291</xmax>
			<ymax>109</ymax>
		</bndbox>
	</object>
	<object>
		<name>text</name>
		<pose>Unspecified</pose>
		<truncated>0</truncated>
		<difficult>0</difficult>
		<bndbox>
			<xmin>404</xmin>
			<ymin>134</ymin>
			<xmax>441</xmax>
			<ymax>163</ymax>
		</bndbox>
	</object>
	<object>
		<name>text</name>
		<pose>Unspecified</pose>
		<truncated>0</truncated>
		<difficult>0</difficult>
		<bndbox>
			<xmin>449</xmin>
			<ymin>125</ymin>
			<xmax>525</xmax>
			<ymax>166</ymax>
		</bndbox>
	</object>
	<object>
		<name>text</name>
		<pose>Unspecified</pose>
		<truncated>0</truncated>
		<difficult>0</difficult>
		<bndbox>
			<xmin>202</xmin>
			<ymin>165</ymin>
			<xmax>228</xmax>
			<ymax>203</ymax>
		</bndbox>
	</object>
	<object>
		<name>text</name>
		<pose>Unspecified</pose>
		<truncated>0</truncated>
		<difficult>0</difficult>
		<bndbox>
			<xmin>235</xmin>
			<ymin>162</ymin>
			<xmax>309</xmax>
			<ymax>195</ymax>
		</bndbox>
	</object>
	<object>
		<name>text</name>
		<pose>Unspecified</pose>
		<truncated>0</truncated>
		<difficult>0</difficult>
		<bndbox>
			<xmin>314</xmin>
			<ymin>165</ymin>
			<xmax>361</xmax>
			<ymax>197</ymax>
		</bndbox>
	</object>
	<object>
		<name>text</name>
		<pose>Unspecified</pose>
		<truncated>0</truncated>
		<difficult>0</difficult>
		<bndbox>
			<xmin>362</xmin>
			<ymin>165</ymin>
			<xmax>414</xmax>
			<ymax>198</ymax>
		</bndbox>
	</object>
	<object>
		<name>text</name>
		<pose>Unspecified</pose>
		<truncated>0</truncated>
		<difficult>0</difficult>
		<bndbox>
			<xmin>276</xmin>
			<ymin>216</ymin>
			<xmax>309</xmax>
			<ymax>251</ymax>
		</bndbox>
	</object>
	<object>
		<name>text</name>
		<pose>Unspecified</pose>
		<truncated>0</truncated>
		<difficult>0</difficult>
		<bndbox>
			<xmin>373</xmin>
			<ymin>225</ymin>
			<xmax>408</xmax>
			<ymax>254</ymax>
		</bndbox>
	</object>
	<object>
		<name>text</name>
		<pose>Unspecified</pose>
		<truncated>0</truncated>
		<difficult>0</difficult>
		<bndbox>
			<xmin>414</xmin>
			<ymin>219</ymin>
			<xmax>496</xmax>
			<ymax>258</ymax>
		</bndbox>
	</object>
	<object>
		<name>text</name>
		<pose>Unspecified</pose>
		<truncated>0</truncated>
		<difficult>0</difficult>
		<bndbox>
			<xmin>703</xmin>
			<ymin>242</ymin>
			<xmax>789</xmax>
			<ymax>272</ymax>
		</bndbox>
	</object>
	<object>
		<name>text</name>
		<pose>Unspecified</pose>
		<truncated>0</truncated>
		<difficult>0</difficult>
		<bndbox>
			<xmin>425</xmin>
			<ymin>270</ymin>
			<xmax>458</xmax>
			<ymax>305</ymax>
		</bndbox>
	</object>
	<object>
		<name>text</name>
		<pose>Unspecified</pose>
		<truncated>0</truncated>
		<difficult>0</difficult>
		<bndbox>
			<xmin>201</xmin>
			<ymin>304</ymin>
			<xmax>284</xmax>
			<ymax>342</ymax>
		</bndbox>
	</object>
	<object>
		<name>text</name>
		<pose>Unspecified</pose>
		<truncated>0</truncated>
		<difficult>0</difficult>
		<bndbox>
			<xmin>296</xmin>
			<ymin>318</ymin>
			<xmax>436</xmax>
			<ymax>355</ymax>
		</bndbox>
	</object>
	<object>
		<name>text</name>
		<pose>Unspecified</pose>
		<truncated>0</truncated>
		<difficult>0</difficult>
		<bndbox>
			<xmin>445</xmin>
			<ymin>318</ymin>
			<xmax>522</xmax>
			<ymax>362</ymax>
		</bndbox>
	</object>
	<object>
		<name>text</name>
		<pose>Unspecified</pose>
		<truncated>0</truncated>
		<difficult>0</difficult>
		<bndbox>
			<xmin>653</xmin>
			<ymin>340</ymin>
			<xmax>689</xmax>
			<ymax>372</ymax>
		</bndbox>
	</object>
	<object>
		<name>text</name>
		<pose>Unspecified</pose>
		<truncated>0</truncated>
		<difficult>0</difficult>
		<bndbox>
			<xmin>789</xmin>
			<ymin>244</ymin>
			<xmax>856</xmax>
			<ymax>282</ymax>
		</bndbox>
	</object>
	<object>
		<name>text</name>
		<pose>Unspecified</pose>
		<truncated>0</truncated>
		<difficult>0</difficult>
		<bndbox>
			<xmin>861</xmin>
			<ymin>248</ymin>
			<xmax>969</xmax>
			<ymax>297</ymax>
		</bndbox>
	</object>
	<object>
		<name>text</name>
		<pose>Unspecified</pose>
		<truncated>0</truncated>
		<difficult>0</difficult>
		<bndbox>
			<xmin>692</xmin>
			<ymin>285</ymin>
			<xmax>795</xmax>
			<ymax>326</ymax>
		</bndbox>
	</object>
	<object>
		<name>text</name>
		<pose>Unspecified</pose>
		<truncated>0</truncated>
		<difficult>0</difficult>
		<bndbox>
			<xmin>892</xmin>
			<ymin>308</ymin>
			<xmax>936</xmax>
			<ymax>342</ymax>
		</bndbox>
	</object>
	<object>
		<name>text</name>
		<pose>Unspecified</pose>
		<truncated>0</truncated>
		<difficult>0</difficult>
		<bndbox>
			<xmin>941</xmin>
			<ymin>316</ymin>
			<xmax>971</xmax>
			<ymax>352</ymax>
		</bndbox>
	</object>
	<object>
		<name>text</name>
		<pose>Unspecified</pose>
		<truncated>0</truncated>
		<difficult>0</difficult>
		<bndbox>
			<xmin>701</xmin>
			<ymin>342</ymin>
			<xmax>789</xmax>
			<ymax>378</ymax>
		</bndbox>
	</object>
	<object>
		<name>text</name>
		<pose>Unspecified</pose>
		<truncated>0</truncated>
		<difficult>0</difficult>
		<bndbox>
			<xmin>801</xmin>
			<ymin>347</ymin>
			<xmax>869</xmax>
			<ymax>383</ymax>
		</bndbox>
	</object>
	<object>
		<name>text</name>
		<pose>Unspecified</pose>
		<truncated>0</truncated>
		<difficult>0</difficult>
		<bndbox>
			<xmin>870</xmin>
			<ymin>362</ymin>
			<xmax>1003</xmax>
			<ymax>410</ymax>
		</bndbox>
	</object>
	<object>
		<name>text</name>
		<pose>Unspecified</pose>
		<truncated>0</truncated>
		<difficult>0</difficult>
		<bndbox>
			<xmin>248</xmin>
			<ymin>354</ymin>
			<xmax>346</xmax>
			<ymax>394</ymax>
		</bndbox>
	</object>
	<object>
		<name>text</name>
		<pose>Unspecified</pose>
		<truncated>0</truncated>
		<difficult>0</difficult>
		<bndbox>
			<xmin>354</xmin>
			<ymin>365</ymin>
			<xmax>449</xmax>
			<ymax>402</ymax>
		</bndbox>
	</object>
	<object>
		<name>text</name>
		<pose>Unspecified</pose>
		<truncated>0</truncated>
		<difficult>0</difficult>
		<bndbox>
			<xmin>457</xmin>
			<ymin>369</ymin>
			<xmax>581</xmax>
			<ymax>409</ymax>
		</bndbox>
	</object>
	<object>
		<name>text</name>
		<pose>Unspecified</pose>
		<truncated>0</truncated>
		<difficult>0</difficult>
		<bndbox>
			<xmin>587</xmin>
			<ymin>376</ymin>
			<xmax>657</xmax>
			<ymax>414</ymax>
		</bndbox>
	</object>
	<object>
		<name>text</name>
		<pose>Unspecified</pose>
		<truncated>0</truncated>
		<difficult>0</difficult>
		<bndbox>
			<xmin>667</xmin>
			<ymin>384</ymin>
			<xmax>793</xmax>
			<ymax>434</ymax>
		</bndbox>
	</object>
	<object>
		<name>text</name>
		<pose>Unspecified</pose>
		<truncated>0</truncated>
		<difficult>0</difficult>
		<bndbox>
			<xmin>801</xmin>
			<ymin>398</ymin>
			<xmax>861</xmax>
			<ymax>443</ymax>
		</bndbox>
	</object>
	<object>
		<name>text</name>
		<pose>Unspecified</pose>
		<truncated>0</truncated>
		<difficult>0</difficult>
		<bndbox>
			<xmin>861</xmin>
			<ymin>404</ymin>
			<xmax>936</xmax>
			<ymax>448</ymax>
		</bndbox>
	</object>
	<object>
		<name>text</name>
		<pose>Unspecified</pose>
		<truncated>0</truncated>
		<difficult>0</difficult>
		<bndbox>
			<xmin>201</xmin>
			<ymin>403</ymin>
			<xmax>349</xmax>
			<ymax>455</ymax>
		</bndbox>
	</object>
	<object>
		<name>text</name>
		<pose>Unspecified</pose>
		<truncated>0</truncated>
		<difficult>0</difficult>
		<bndbox>
			<xmin>361</xmin>
			<ymin>426</ymin>
			<xmax>415</xmax>
			<ymax>454</ymax>
		</bndbox>
	</object>
	<object>
		<name>text</name>
		<pose>Unspecified</pose>
		<truncated>0</truncated>
		<difficult>0</difficult>
		<bndbox>
			<xmin>424</xmin>
			<ymin>414</ymin>
			<xmax>474</xmax>
			<ymax>451</ymax>
		</bndbox>
	</object>
	<object>
		<name>text</name>
		<pose>Unspecified</pose>
		<truncated>0</truncated>
		<difficult>0</difficult>
		<bndbox>
			<xmin>339</xmin>
			<ymin>469</ymin>
			<xmax>377</xmax>
			<ymax>506</ymax>
		</bndbox>
	</object>
	<object>
		<name>text</name>
		<pose>Unspecified</pose>
		<truncated>0</truncated>
		<difficult>0</difficult>
		<bndbox>
			<xmin>517</xmin>
			<ymin>475</ymin>
			<xmax>553</xmax>
			<ymax>513</ymax>
		</bndbox>
	</object>
	<object>
		<name>text</name>
		<pose>Unspecified</pose>
		<truncated>0</truncated>
		<difficult>0</difficult>
		<bndbox>
			<xmin>555</xmin>
			<ymin>478</ymin>
			<xmax>625</xmax>
			<ymax>519</ymax>
		</bndbox>
	</object>
	<object>
		<name>text</name>
		<pose>Unspecified</pose>
		<truncated>0</truncated>
		<difficult>0</difficult>
		<bndbox>
			<xmin>631</xmin>
			<ymin>479</ymin>
			<xmax>709</xmax>
			<ymax>522</ymax>
		</bndbox>
	</object>
	<object>
		<name>text</name>
		<pose>Unspecified</pose>
		<truncated>0</truncated>
		<difficult>0</difficult>
		<bndbox>
			<xmin>341</xmin>
			<ymin>514</ymin>
			<xmax>487</xmax>
			<ymax>561</ymax>
		</bndbox>
	</object>
	<object>
		<name>text</name>
		<pose>Unspecified</pose>
		<truncated>0</truncated>
		<difficult>0</difficult>
		<bndbox>
			<xmin>229</xmin>
			<ymin>509</ymin>
			<xmax>333</xmax>
			<ymax>542</ymax>
		</bndbox>
	</object>
	<object>
		<name>text</name>
		<pose>Unspecified</pose>
		<truncated>0</truncated>
		<difficult>0</difficult>
		<bndbox>
			<xmin>933</xmin>
			<ymin>530</ymin>
			<xmax>1017</xmax>
			<ymax>576</ymax>
		</bndbox>
	</object>
	<object>
		<name>text</name>
		<pose>Unspecified</pose>
		<truncated>0</truncated>
		<difficult>0</difficult>
		<bndbox>
			<xmin>754</xmin>
			<ymin>151</ymin>
			<xmax>786</xmax>
			<ymax>184</ymax>
		</bndbox>
	</object>
</annotation>
